control.v
// Control Block 

module control(
    input wire [6:0] op_code,
    output wire branch,
    output wire mem_read,
    output wire mem_to_reg,
    output wire [1:0] alu_op,
    output wire mem_write,
    output wire alu_src,
    output wire reg_write_en
    );

    localparam R_type = 7'b0110011;
    localparam I_op_type = 7'b0010011;
    localparam I_load_type = 7'b0000011;
    localparam S_type = 7'b0100011;
    localparam B_type = 7'b1100011;

    reg branch_reg, mem_read_reg, mem_to_reg_reg, mem_write_reg, alu_src_reg, reg_write_en_reg;
    reg [1:0] alu_op_reg;

    assign branch = branch_reg;
    assign mem_read = mem_read_reg;
    assign mem_to_reg = mem_to_reg_reg;
    assign alu_op = alu_op_reg;
    assign mem_write = mem_write_reg;
    assign alu_src = alu_src_reg;
    assign reg_write_en = reg_write_en_reg;

    always @(*) begin
        case(op_code)
            R_type: begin
                branch_reg = 1'b0;
                mem_read_reg = 1'b0;
                mem_to_reg_reg = 1'b0;
                alu_op_reg = 2'b10;
                mem_write_reg = 1'b0;
                alu_src_reg = 1'b0;
                reg_write_en_reg = 1'b1;
            end
            I_op_type: begin
                branch_reg = 1'b0;
                mem_read_reg = 1'b0;
                mem_to_reg_reg = 1'b0;
                alu_op_reg = 2'b00;
                mem_write_reg = 1'b0;
                alu_src_reg = 1'b1;
                reg_write_en_reg = 1'b1;
            end
            I_load_type: begin
                branch_reg = 1'b0;
                mem_read_reg = 1'b1;
                mem_to_reg_reg = 1'b1;
                alu_op_reg = 2'b00;
                mem_write_reg = 1'b0;
                alu_src_reg = 1'b1;
                reg_write_en_reg = 1'b1;
            end
            S_type: begin
                branch_reg = 1'b0;
                mem_read_reg = 1'b0;
                mem_to_reg_reg = 1'b0;
                alu_op_reg = 2'b00;
                mem_write_reg = 1'b1;
                alu_src_reg = 1'b1;
                reg_write_en_reg = 1'b0;
            end
            B_type: begin
                branch_reg = 1'b1;
                mem_read_reg = 1'b0;
                mem_to_reg_reg = 1'b0;
                alu_op_reg = 2'b01;
                mem_write_reg = 1'b0;
                alu_src_reg = 1'b0;
                reg_write_en_reg = 1'b0;
            end
            // J_type: begin
            //     branch_reg = 1'b1;
            //     mem_read_reg = 1'b0;
            //     mem_to_reg_reg = 1'b0;
            //     alu_op_reg = 2'b00;
            //     mem_write_reg = 1'b0;
            //     alu_src_reg = 1'b0;
            //     reg_write_en_reg = 1'b0;
            // end
            default: begin
                branch_reg = 1'b0;
                mem_read_reg = 1'b0;
                mem_to_reg_reg = 1'b0;
                alu_op_reg = 2'b00;
                mem_write_reg = 1'b0;
                alu_src_reg = 1'b0;
                reg_write_en_reg = 1'b0;
            end
        endcase
    end

endmodule

SEQ/control_tb.v
`timescale 1ns/1ps

`include "control.v"

module control_tb;
    // Inputs
    reg [6:0] op_code;
    
    // Outputs
    wire branch;
    wire mem_read;
    wire mem_to_reg;
    wire [1:0] alu_op;
    wire mem_write;
    wire alu_src;
    wire reg_write_en;
    
    // Test counter
    integer test_count = 0;
    integer pass_count = 0;
    
    // Instantiate the Unit Under Test (UUT)
    control uut(
        .op_code(op_code),
        .branch(branch),
        .mem_read(mem_read),
        .mem_to_reg(mem_to_reg),
        .alu_op(alu_op),
        .mem_write(mem_write),
        .alu_src(alu_src),
        .reg_write_en(reg_write_en)
    );
    
    // Task to run individual tests
    task run_test;
        input [7:0] test_op_code;
        input exp_branch;
        input exp_mem_read;
        input exp_mem_to_reg;
        input [1:0] exp_alu_op;
        input exp_mem_write;
        input exp_alu_src;
        input exp_reg_write_en;
        input [128:0] test_name;
        begin
            test_count = test_count + 1;
            
            // Apply inputs
            op_code = test_op_code;
            #10; // Wait for outputs to stabilize
            
            // Display test information
            $display("\nTest Case %0d: %s", test_count, test_name);
            $display("OpCode: %b", op_code);
            $display("Expected outputs:");
            $display("  branch=%b, mem_read=%b, mem_to_reg=%b, alu_op=%b",
                    exp_branch, exp_mem_read, exp_mem_to_reg, exp_alu_op);
            $display("  mem_write=%b, alu_src=%b, reg_write_en=%b",
                    exp_mem_write, exp_alu_src, exp_reg_write_en);
            $display("Actual outputs:");
            $display("  branch=%b, mem_read=%b, mem_to_reg=%b, alu_op=%b",
                    branch, mem_read, mem_to_reg, alu_op);
            $display("  mem_write=%b, alu_src=%b, reg_write_en=%b",
                    mem_write, alu_src, reg_write_en);
            
            // Check if all outputs match expected values
            if (branch === exp_branch &&
                mem_read === exp_mem_read &&
                mem_to_reg === exp_mem_to_reg &&
                alu_op === exp_alu_op &&
                mem_write === exp_mem_write &&
                alu_src === exp_alu_src &&
                reg_write_en === exp_reg_write_en) begin
                $display("Status: PASS");
                pass_count = pass_count + 1;
            end else begin
                $display("Status: FAIL");
                if (branch !== exp_branch) $display("  branch mismatch!");
                if (mem_read !== exp_mem_read) $display("  mem_read mismatch!");
                if (mem_to_reg !== exp_mem_to_reg) $display("  mem_to_reg mismatch!");
                if (alu_op !== exp_alu_op) $display("  alu_op mismatch!");
                if (mem_write !== exp_mem_write) $display("  mem_write mismatch!");
                if (alu_src !== exp_alu_src) $display("  alu_src mismatch!");
                if (reg_write_en !== exp_reg_write_en) $display("  reg_write_en mismatch!");
            end
        end
    endtask
    
    // Main test sequence
    initial begin
        $dumpfile("control_tb.vcd");
        $dumpvars(0, control_tb);
        
        // Initialize inputs
        op_code = 0;
        #100;
        
        // Test R-type instructions (add, sub, and, or, etc.)
        run_test(
            8'b0110011, // op_code
            1'b0,       // branch
            1'b0,       // mem_read
            1'b0,       // mem_to_reg
            2'b10,      // alu_op
            1'b0,       // mem_write
            1'b0,       // alu_src
            1'b1,       // reg_write_en
            "R-type instruction"
        );
        
        // Test I-type ALU instructions (addi, andi, ori, etc.)
        run_test(
            8'b0010011, // op_code
            1'b0,       // branch
            1'b0,       // mem_read
            1'b0,       // mem_to_reg
            2'b00,      // alu_op
            1'b0,       // mem_write
            1'b1,       // alu_src
            1'b1,       // reg_write_en
            "I-type ALU instruction"
        );
        
        // Test I-type Load instructions (lw, lb, etc.)
        run_test(
            8'b0000011, // op_code
            1'b0,       // branch
            1'b1,       // mem_read
            1'b1,       // mem_to_reg
            2'b00,      // alu_op
            1'b0,       // mem_write
            1'b1,       // alu_src
            1'b1,       // reg_write_en
            "I-type Load instruction"
        );
        
        // Test S-type instructions (sw, sb, etc.)
        run_test(
            8'b0100011, // op_code
            1'b0,       // branch
            1'b0,       // mem_read
            1'b0,       // mem_to_reg
            2'b00,      // alu_op
            1'b1,       // mem_write
            1'b1,       // alu_src
            1'b0,       // reg_write_en
            "S-type instruction"
        );
        
        // Test B-type instructions (beq, bne, etc.)
        run_test(
            8'b1100011, // op_code
            1'b1,       // branch
            1'b0,       // mem_read
            1'b0,       // mem_to_reg
            2'b01,      // alu_op
            1'b0,       // mem_write
            1'b0,       // alu_src
            1'b0,       // reg_write_en
            "B-type instruction"
        );
        
        // Test invalid/unsupported opcode
        run_test(
            8'b1111111, // op_code
            1'b0,       // branch
            1'b0,       // mem_read
            1'b0,       // mem_to_reg
            2'b00,      // alu_op
            1'b0,       // mem_write
            1'b0,       // alu_src
            1'b0,       // reg_write_en
            "Invalid opcode"
        );
        
        // Display test summary
        #10;
        $display("\n=== Test Summary ===");
        $display("Total Tests: %0d", test_count);
        $display("Passed: %0d", pass_count);
        $display("Failed: %0d", test_count - pass_count);
        $display("==================\n");
        
        $finish;
    end

endmodule

SEQ/control_tb.vcd
$date
	Fri Mar  7 06:29:46 2025
$end
$version
	Icarus Verilog
$end
$timescale
	1ps
$end
$scope module control_tb $end
$var wire 1 ! reg_write_en $end
$var wire 1 " mem_write $end
$var wire 1 # mem_to_reg $end
$var wire 1 $ mem_read $end
$var wire 1 % branch $end
$var wire 1 & alu_src $end
$var wire 2 ' alu_op [1:0] $end
$var reg 7 ( op_code [6:0] $end
$var integer 32 ) pass_count [31:0] $end
$var integer 32 * test_count [31:0] $end
$scope module uut $end
$var wire 2 + alu_op [1:0] $end
$var wire 1 & alu_src $end
$var wire 1 % branch $end
$var wire 1 $ mem_read $end
$var wire 1 # mem_to_reg $end
$var wire 1 " mem_write $end
$var wire 7 , op_code [6:0] $end
$var wire 1 ! reg_write_en $end
$var parameter 7 - B_type $end
$var parameter 7 . I_load_type $end
$var parameter 7 / I_op_type $end
$var parameter 7 0 R_type $end
$var parameter 7 1 S_type $end
$var reg 2 2 alu_op_reg [1:0] $end
$var reg 1 3 alu_src_reg $end
$var reg 1 4 branch_reg $end
$var reg 1 5 mem_read_reg $end
$var reg 1 6 mem_to_reg_reg $end
$var reg 1 7 mem_write_reg $end
$var reg 1 8 reg_write_en_reg $end
$upscope $end
$scope task run_test $end
$var reg 2 9 exp_alu_op [1:0] $end
$var reg 1 : exp_alu_src $end
$var reg 1 ; exp_branch $end
$var reg 1 < exp_mem_read $end
$var reg 1 = exp_mem_to_reg $end
$var reg 1 > exp_mem_write $end
$var reg 1 ? exp_reg_write_en $end
$var reg 129 @ test_name [128:0] $end
$var reg 8 A test_op_code [7:0] $end
$upscope $end
$upscope $end
$enddefinitions $end
$comment Show the parameter values. $end
$dumpall
b100011 1
b110011 0
b10011 /
b11 .
b1100011 -
$end
#0
$dumpvars
bx A
bx @
x?
x>
x=
x<
x;
x:
bx 9
08
07
06
05
04
03
b0 2
b0 ,
b0 +
b0 *
b0 )
b0 (
b0 '
0&
0%
0$
0#
0"
0!
$end
#100000
1!
18
b10 '
b10 +
b10 2
b110011 (
b110011 ,
b1 *
b101110100011110010111000001100101001000000110100101101110011100110111010001110010011101010110001101110100011010010110111101101110 @
1?
0:
0>
b10 9
0=
0<
0;
b110011 A
#110000
1&
13
b0 '
b0 +
b0 2
b10011 (
b10011 ,
b10 *
b100100000010000010100110001010101001000000110100101101110011100110111010001110010011101010110001101110100011010010110111101101110 @
1:
b0 9
b10011 A
b1 )
#120000
1#
16
1$
15
b11 (
b11 ,
b11 *
b1001100011011110110000101100100001000000110100101101110011100110111010001110010011101010110001101110100011010010110111101101110 @
1=
1<
b11 A
b10 )
#130000
0!
08
1"
17
0#
06
0$
05
b100011 (
b100011 ,
b100 *
b101110100011110010111000001100101001000000110100101101110011100110111010001110010011101010110001101110100011010010110111101101110 @
0?
1>
0=
0<
b100011 A
b11 )
#140000
0&
03
0"
07
b1 '
b1 +
b1 2
1%
14
b1100011 (
b1100011 ,
b101 *
0:
0>
b1 9
1;
b1100011 A
b100 )
#150000
b0 '
b0 +
b0 2
0%
04
b1111111 (
b1111111 ,
b110 *
b100100101101110011101100110000101101100011010010110010000100000011011110111000001100011011011110110010001100101 @
b0 9
0;
b1111111 A
b101 )
#160000
b110 )
