SEQ/data_memory.v
module data_memory #(parameter DATA_WIDTH = 64, parameter ADDR_WIDTH = 10) (
    input wire clk,
    input wire reset,                // Active-high asynchronous reset
    input wire [ADDR_WIDTH-1:0] addr,
    input wire [DATA_WIDTH-1:0] write_data,
    input wire mem_write,
    input wire mem_read,
    output wire [DATA_WIDTH-1:0] read_data
);
    // Memory array
    reg [DATA_WIDTH-1:0] mem [(2**ADDR_WIDTH)-1:0];
    integer i; // Declare the loop variable outside the always block

    // Write to memory with asynchronous reset
    always @(posedge clk or posedge reset) begin
        if (reset) begin
            // Clear entire memory on reset
            for (i = 0; i < (2**ADDR_WIDTH); i = i + 1) begin
                mem[i] = 0; // Use '=' for blocking assignment in reset loops
            end
        end 
        else if (mem_write) begin
            mem[addr] <= write_data; // Non-blocking assignment for sequential logic
        end
    end

    reg [DATA_WIDTH-1:0] read_data_reg; // Declare read_data as a reg for continuous assignment

    assign read_data = read_data_reg; // Assign read_data to read_data_reg
    
    always @(*) begin
        if (mem_read) begin
            read_data_reg = mem[addr]; // Read data from memory
        end
        else begin
            read_data_reg = 0; // Output 0 if mem_read is low (or High-z if required)
        end
    end
endmodule

SEQ/data_memory_tb.v
`timescale 1ns / 1ps
`include "data_memory.v"

module data_memory_tb;
    localparam DATA_WIDTH = 64;
    localparam ADDR_WIDTH = 10;

    reg clk = 0;
    reg rst = 1;
    reg [ADDR_WIDTH-1:0] addr;
    reg [DATA_WIDTH-1:0] write_data;
    reg mem_write;
    reg mem_read;
    wire [DATA_WIDTH-1:0] read_data;

    data_memory #(DATA_WIDTH, ADDR_WIDTH) uut (
        .clk(clk), .reset(rst), .addr(addr), .write_data(write_data),
        .mem_write(mem_write), .mem_read(mem_read), .read_data(read_data)
    );

    always #10 clk = ~clk;

    initial begin
        $dumpfile("data_memory_tb.vcd");
        $dumpvars(1, data_memory_tb);
        mem_read = 0; mem_write = 0; #10
        rst = 1; #10 rst = 0;

        // Test 1: Write and read from address 5
        addr = 5; write_data = 64'hCAFEBABEDEADBEEF; mem_write = 1; #20; mem_write = 0;
        mem_read = 1; #20; $display("Addr 5: %h", read_data); mem_read = 0;

        // Test 2: Write and read from address 0
        addr = 0; write_data = 64'h1234567890ABCDEF; mem_write = 1; #20; mem_write = 0;
        mem_read = 1; #20; $display("Addr 0: %h", read_data); mem_read = 0;

        // Test 3: Write and read from max address (1023)
        addr = 1023; write_data = 64'hFFFFFFFFFFFFFFFF; mem_write = 1; #20; mem_write = 0;
        mem_read = 1; #20; $display("Addr 1023: %h", read_data); mem_read = 0;

        // Edge case: No write, just read
        addr = 10; mem_read = 1; #20; $display("Addr 10 (unwritten): %h", read_data); mem_read = 0;

        // Edge case: Write to address 1, then reset
        addr = 1; write_data = 64'hA5A5A5A5A5A5A5A5; mem_write = 1; #20; rst = 1; #20; rst = 0; mem_write = 0;
        mem_read = 1; #20; $display("Addr 1 after reset: %h", read_data); mem_read = 0;

        #20; $finish;
    end
endmodule

SEQ/data_memory_tb.vcd
$date
	Fri Mar  7 07:07:43 2025
$end
$version
	Icarus Verilog
$end
$timescale
	1ps
$end
$scope module data_memory_tb $end
$var wire 64 ! read_data [63:0] $end
$var parameter 32 " ADDR_WIDTH $end
$var parameter 32 # DATA_WIDTH $end
$var reg 10 $ addr [9:0] $end
$var reg 1 % clk $end
$var reg 1 & mem_read $end
$var reg 1 ' mem_write $end
$var reg 1 ( rst $end
$var reg 64 ) write_data [63:0] $end
$upscope $end
$enddefinitions $end
$comment Show the parameter values. $end
$dumpall
b1000000 #
b1010 "
$end
#0
$dumpvars
bx )
1(
0'
0&
0%
bx $
b0 !
$end
#10000
1%
#20000
1'
b1100101011111110101110101011111011011110101011011011111011101111 )
b101 $
0(
0%
#30000
1%
#40000
b1100101011111110101110101011111011011110101011011011111011101111 !
0%
1&
0'
#50000
1%
#60000
b0 !
0%
1'
b1001000110100010101100111100010010000101010111100110111101111 )
b0 $
0&
#70000
1%
#80000
b1001000110100010101100111100010010000101010111100110111101111 !
0%
1&
0'
#90000
1%
#100000
b0 !
0%
1'
b1111111111111111111111111111111111111111111111111111111111111111 )
b1111111111 $
0&
#110000
1%
#120000
b1111111111111111111111111111111111111111111111111111111111111111 !
0%
1&
0'
#130000
1%
#140000
b0 !
0%
b1010 $
1&
#150000
1%
#160000
0%
1'
b1010010110100101101001011010010110100101101001011010010110100101 )
b1 $
0&
#170000
1%
#180000
0%
1(
#190000
1%
#200000
0%
1&
0'
0(
#210000
1%
#220000
0%
0&
