imm_gen.v
module imm_gen(
    input wire [31:0] instr,
    output reg [63:0] imm
);

    localparam I_op_type = 7'b0010011;
    localparam I_load_type = 7'b0000011;
    localparam S_type = 7'b0100011;
    localparam B_type = 7'b1100011;

    wire [6:0] opcode;
    assign opcode = instr[6:0];

    always @(*) begin
        case(opcode)
            I_op_type, I_load_type: begin
                imm = {{52{instr[31]}}, instr[31:20]};
            end

            S_type: begin
                imm = {{52{instr[31]}}, instr[31:25], instr[11:7]};
            end

            B_type: begin
                imm = {{52{instr[31]}}, instr[31], instr[7], 
                      instr[30:25], instr[11:8]};
            end

            default: begin
                imm = 64'b0;
            end
        endcase
    end

endmodule

SEQ/imm_gen_tb.v
`timescale 1ns/1ps

`include "imm_gen.v"

module imm_gen_TB;
    reg [31:0] instr;
    wire [63:0] imm;
    
    // Test counter
    integer test_count = 0;
    integer pass_count = 0;
    
    imm_gen uut(
        .instr(instr),
        .imm(imm)
    );

    task run_test;
        input [31:0] test_instr;
        input [63:0] expected_imm;
        begin
            test_count = test_count + 1;
            instr = test_instr;
            #10;
            
            $display("\nTest Case %0d:", test_count);
            $display("Instruction: %b %b %b %b %b %b %b %b", 
                    instr[31:28], instr[27:24], instr[23:20], instr[19:16],
                    instr[15:12], instr[11:8], instr[7:4], instr[3:0]);
            $display("Opcode: %b", instr[6:0]);
            $display("Expected Immediate: %h", expected_imm);
            $display("Actual Immediate: %h", imm);
            
            if (imm === expected_imm) begin
                $display("Status: PASS");
                pass_count = pass_count + 1;
            end else begin
                $display("Status: FAIL");
                $display("Immediate value mismatch!");
            end
        end
    endtask

    initial begin
        $dumpfile("imm_gen_TB.vcd");
        $dumpvars(1, uut);

        // 1
        // I-type instruction tests (op-type)
        // ADDI x1, x2, 12
        run_test(32'b0000_0000_1100_0001_0000_0000_1001_0011,
                64'h000000000000000C);

        //2
        // ADDI x1, x2, -12
        run_test(32'b1111_1111_1100_0001_0000_0000_1001_0011,
                64'hFFFFFFFFFFFFFFFC);

        //3
        // I-type instruction tests (load-type)
        // LW x1, 16(x2)
        run_test(32'b0000_0001_0000_0001_0010_0000_1000_0011,
                64'h0000000000000010);

        //4
        // LW x1, -16(x2)
        run_test(32'b1111_1111_0000_0001_0010_0000_1000_0011,
                64'hFFFFFFFFFFFFFFF0);

        //5
        // S-type instruction tests
        // SW x1, 20(x2)
        run_test(32'b0000_0010_0001_0001_0010_1010_0010_0011,
                64'h0000000000000034);

        //6
        // SW x1, -20(x2)
        run_test(32'b1111_1110_0001_0001_0010_1110_0010_0011,
                64'hFFFFFFFFFFFFFFFC);

        //7
        // B-type instruction tests
        // BEQ x1, x2, 16
        run_test(32'b0000_0000_0010_0000_1000_1000_0110_0011,
                64'h0000000000000010);

        //8
        // BEQ x1, x2, -16
        run_test(32'b1111_1110_0010_0000_1000_1000_1110_0011,
                64'hFFFFFFFFFFFFFFF0);

        //9
        // Edge cases
        // Maximum positive immediate for I-type
        run_test(32'b0111_1111_1111_0000_0000_0000_0001_0011,
                64'h00000000000007FF);

        //10
        // Maximum negative immediate for I-type
        run_test(32'b1000_0000_0000_0000_0000_0000_0001_0011,
                64'hFFFFFFFFFFFFF800);

        //11
        // Invalid opcode test
        run_test(32'b0000_0000_0000_0000_0000_0000_0111_1111,
                64'h0000000000000000);

        // Report Results
        #10;
        $display("\n=== Test Summary ===");
        $display("Total Tests: %0d", test_count);
        $display("Passed: %0d", pass_count);
        $display("Failed: %0d", test_count - pass_count);
        $display("==================\n");
        
        $finish;
    end

endmodule

SEQ/imm_gen_TB.vcd
$date
	Fri Mar  7 06:44:51 2025
$end
$version
	Icarus Verilog
$end
$timescale
	1ps
$end
$scope module imm_gen_TB $end
$scope module uut $end
$var wire 32 ! instr [31:0] $end
$var wire 7 " opcode [6:0] $end
$var parameter 7 # B_type $end
$var parameter 7 $ I_load_type $end
$var parameter 7 % I_op_type $end
$var parameter 7 & S_type $end
$var reg 64 ' imm [63:0] $end
$upscope $end
$upscope $end
$enddefinitions $end
$comment Show the parameter values. $end
$dumpall
b100011 &
b10011 %
b11 $
b1100011 #
$end
#0
$dumpvars
b1100 '
b10011 "
b110000010000000010010011 !
$end
#10000
b1111111111111111111111111111111111111111111111111111111111111100 '
b11111111110000010000000010010011 !
#20000
b10000 '
b11 "
b1000000010010000010000011 !
#30000
b1111111111111111111111111111111111111111111111111111111111110000 '
b11111111000000010010000010000011 !
#40000
b110100 '
b100011 "
b10000100010010101000100011 !
#50000
b1111111111111111111111111111111111111111111111111111111111111100 '
b11111110000100010010111000100011 !
#60000
b10000 '
b1100011 "
b1000001000100001100011 !
#70000
b1111111111111111111111111111111111111111111111111111111111110000 '
b11111110001000001000100011100011 !
#80000
b11111111111 '
b10011 "
b1111111111100000000000000010011 !
#90000
b1111111111111111111111111111111111111111111111111111100000000000 '
b10000000000000000000000000010011 !
#100000
b0 '
b1111111 "
b1111111 !
