SEQ/instruction_mem.v
// Reads decimal values
// module instruction_memory #(
//     parameter MEM_SIZE = 4095,
//     parameter MEM_INIT_FILE = "Test_Vector_Add.txt"
//     // parameter MEM_INIT_FILE = "imemory.txt"
// ) (
//     input wire clk,
//     input wire reset,  // Added reset signal
//     input wire [63:0] addr,
//     output wire [31:0] instr
// );
//     // Memory array
//     reg [7:0] mem [0:MEM_SIZE-1];
    
//     // File reading variables
//     integer file, status, i;
//     integer decimal_value;
    
//     // Initialize memory from file
//     initial begin
//         // Clear memory
//         for (i = 0; i < MEM_SIZE; i = i + 1)
//             mem[i] = 0;
            
//         // Read from file
//         file = $fopen(MEM_INIT_FILE, "r");
//         if (!file) begin
//             $display("Error: Could not open %s", MEM_INIT_FILE);
//             $finish;
//         end
        
//         i = 0;
//         while (!$feof(file) && i < MEM_SIZE) begin
//             status = $fscanf(file, "%d", decimal_value);
//             // Print whatever is read
//             // $display("Read %0d", decimal_value);
//             if (status == 1 && decimal_value >= 0 && decimal_value <= 255) begin
//                 mem[i] = decimal_value;
//                 i = i + 1;
//             end
//         end
        
//         $fclose(file);
//         $display("Loaded %0d bytes from %s", i, MEM_INIT_FILE);
//     end

//     reg [31:0] tmp;
//     assign instr = tmp;

//     // // Read instruction with reset (big-endian)
//     // always @(posedge clk or posedge reset) begin
//     //     if (reset) begin
//     //         tmp <= 32'h0;  // Reset the instruction register to zero
//     //     end else begin
//     //         tmp <= {mem[addr+0], mem[addr+1], mem[addr+2], mem[addr+3]};
//     //     end
//     // end

//     // Read instruction with reset (big-endian)
//     always @(*) 
//     begin
//         tmp <= {mem[addr+0], mem[addr+1], mem[addr+2], mem[addr+3]};
//     end

// endmodule

// Reads hex values
module instruction_memory #(
    parameter MEM_SIZE = 4095,
    parameter MEM_INIT_FILE = "Test_Overflow_code.txt"
) (
    input wire clk,
    input wire reset,  // Added reset signal
    input wire [63:0] addr,
    output wire [31:0] instr
);
    // Memory array
    reg [7:0] mem [0:MEM_SIZE-1];
    
    // File reading variables
    integer file, status, i;
    reg [7:0] hex_value;
    
    // Initialize memory from file
    initial begin
        // Clear memory
        for (i = 0; i < MEM_SIZE; i = i + 1)
            mem[i] = 0;
            
        // Read from file
        file = $fopen(MEM_INIT_FILE, "r");
        if (!file) begin
            $display("Error: Could not open %s", MEM_INIT_FILE);
            $finish;
        end
        
        i = 0;
        while (!$feof(file) && i < MEM_SIZE) begin
            status = $fscanf(file, "%h", hex_value); // Changed to %h for hex format
            if (status == 1) begin
                mem[i] = hex_value;
                i = i + 1;
            end
        end
        
        $fclose(file);
        $display("Loaded %0d bytes from %s", i, MEM_INIT_FILE);
    end

    reg [31:0] tmp;
    assign instr = tmp;

    always @(*) 
    begin
        tmp = {mem[addr+0], mem[addr+1], mem[addr+2], mem[addr+3]};
    end

endmodule

SEQ/instruction_mem_tb.v
`timescale 1ns/1ps
`include "instruction_mem.v"

module instruction_memory_tb;
    reg clk;
    reg reset;
    reg [63:0] addr;
    wire [31:0] instr;
    
    // Test counter
    integer test_count = 0;
    integer pass_count = 0;
    
    instruction_memory #(
        .MEM_SIZE(4095),
        .MEM_INIT_FILE("Test_imemory_2.txt")
    ) imem (
        .clk(clk),
        .reset(reset),
        .addr(addr),
        .instr(instr)
    );

    // Clock generation
    initial begin
        clk = 0;
        forever #5 clk = ~clk;
    end

    // Add GTKWave dumping
    initial begin
        $dumpfile("instruction_memory_tb.vcd");
        $dumpvars(0, instruction_memory_tb);
    end

    task run_test;
        input [63:0] test_addr;
        input [31:0] expected_instr;
        begin
            test_count = test_count + 1;
            addr = test_addr;
            
            @(posedge clk);
            #2;
            
            $display("Test Case %0d:", test_count);
            $display("Address = 0x%h", addr);
            $display("Expected Instruction = 0x%h", expected_instr);
            $display("Actual Instruction   = 0x%h", instr);
            
            if (instr === expected_instr) begin
                $display("Status: PASS\n");
                pass_count = pass_count + 1;
            end else begin
                $display("Status: FAIL\n");
            end
        end
    endtask

    initial begin
        // Initialize signals
        addr = 0;
        reset = 0;
        test_count = 0;
        pass_count = 0;

        $display("Starting Instruction Memory Test");
        
        // Wait for memory initialization
        #10;

        // Test cases for little-endian format
        // Original test cases
        run_test(0, 32'h00500113);    // First instruction (bytes 0-3)
        #10;
        run_test(4, 32'h00a00193);    // Second instruction (bytes 4-7)
        #10;
        run_test(8, 32'h003100b3);    // Third instruction (bytes 8-11)
        #10;
        run_test(12, 32'h40310133);   // Fourth instruction (bytes 12-15)
        #10;
        
        // Additional test cases
        run_test(16, 32'h0021a233);   // Fifth instruction (bytes 16-19)
        #10;
        run_test(20, 32'h0041f2b3);   // Sixth instruction (bytes 20-23)
        #10;
        run_test(24, 32'h00416333);   // Seventh instruction (bytes 24-27)
        #10;
        run_test(28, 32'h004143b3);   // Eighth instruction (bytes 28-31)
        #10;
        run_test(32, 32'h00002437);   // Ninth instruction (bytes 32-35)
        #10;
        run_test(36, 32'h06042223);   // Tenth instruction (bytes 36-39)
        #10;
        run_test(40, 32'h06442483);   // Eleventh instruction (bytes 40-43)
        #10;
        run_test(44, 32'h00119493);   // Twelfth instruction (bytes 44-47)
        #10;
        run_test(48, 32'h00115513);   // Thirteenth instruction (bytes 48-51)
        #10;
        run_test(52, 32'h40115593);   // Fourteenth instruction (bytes 52-55)
        #10;
        run_test(56, 32'h00208663);   // Fifteenth instruction (bytes 56-59)
        #10;
        
        // Report Results
        $display("=== Test Summary ===");
        $display("Total Tests: %0d", test_count);
        $display("Passed: %0d", pass_count);
        $display("Failed: %0d", test_count - pass_count);
        $display("==================\n");
        
        #10 $finish;
    end

endmodule

SEQ/instruction_memory_tb.vcd
$date
	Fri Mar  7 06:19:35 2025
$end
$version
	Icarus Verilog
$end
$timescale
	1ps
$end
$scope module instruction_memory_tb $end
$var wire 32 ! instr [31:0] $end
$var reg 64 " addr [63:0] $end
$var reg 1 # clk $end
$var reg 1 $ reset $end
$var integer 32 % pass_count [31:0] $end
$var integer 32 & test_count [31:0] $end
$scope module imem $end
$var wire 64 ' addr [63:0] $end
$var wire 1 # clk $end
$var wire 32 ( instr [31:0] $end
$var wire 1 $ reset $end
$var parameter 144 ) MEM_INIT_FILE $end
$var parameter 32 * MEM_SIZE $end
$var reg 8 + hex_value [7:0] $end
$var reg 32 , tmp [31:0] $end
$var integer 32 - file [31:0] $end
$var integer 32 . i [31:0] $end
$var integer 32 / status [31:0] $end
$upscope $end
$scope task run_test $end
$var reg 32 0 expected_instr [31:0] $end
$var reg 64 1 test_addr [63:0] $end
$upscope $end
$upscope $end
$enddefinitions $end
$comment Show the parameter values. $end
$dumpall
b111111111111 *
b10101000110010101110011011101000101111101101001011011010110010101101101011011110111001001111001010111110011001000101110011101000111100001110100 )
$end
#0
$dumpvars
bx 1
bx 0
b1 /
b10010000 .
b10000000000000000000000000000011 -
b10100000000000100010011 ,
b0 +
b10100000000000100010011 (
b0 '
b0 &
b0 %
0$
0#
b0 "
b10100000000000100010011 !
$end
#5000
1#
#10000
0#
b1 &
b10100000000000100010011 0
b0 1
#15000
1#
#17000
b1 %
#20000
0#
#25000
1#
#27000
b101000000000000110010011 !
b101000000000000110010011 (
b101000000000000110010011 ,
b100 "
b100 '
b10 &
b101000000000000110010011 0
b100 1
#30000
0#
#35000
1#
#37000
b10 %
#40000
0#
#45000
1#
#47000
b1100010000000010110011 !
b1100010000000010110011 (
b1100010000000010110011 ,
b1000 "
b1000 '
b11 &
b1100010000000010110011 0
b1000 1
#50000
0#
#55000
1#
#57000
b11 %
#60000
0#
#65000
1#
#67000
b1000000001100010000000100110011 !
b1000000001100010000000100110011 (
b1000000001100010000000100110011 ,
b1100 "
b1100 '
b100 &
b1000000001100010000000100110011 0
b1100 1
#70000
0#
#75000
1#
#77000
b100 %
#80000
0#
#85000
1#
#87000
b1000011010001000110011 !
b1000011010001000110011 (
b1000011010001000110011 ,
b10000 "
b10000 '
b101 &
b1000011010001000110011 0
b10000 1
#90000
0#
#95000
1#
#97000
b101 %
#100000
0#
#105000
1#
#107000
b10000011111001010110011 !
b10000011111001010110011 (
b10000011111001010110011 ,
b10100 "
b10100 '
b110 &
b10000011111001010110011 0
b10100 1
#110000
0#
#115000
1#
#117000
b110 %
#120000
0#
#125000
1#
#127000
b10000010110001100110011 !
b10000010110001100110011 (
b10000010110001100110011 ,
b11000 "
b11000 '
b111 &
b10000010110001100110011 0
b11000 1
#130000
0#
#135000
1#
#137000
b111 %
#140000
0#
#145000
1#
#147000
b10000010100001110110011 !
b10000010100001110110011 (
b10000010100001110110011 ,
b11100 "
b11100 '
b1000 &
b10000010100001110110011 0
b11100 1
#150000
0#
#155000
1#
#157000
b1000 %
#160000
0#
#165000
1#
#167000
b10010000110111 !
b10010000110111 (
b10010000110111 ,
b100000 "
b100000 '
b1001 &
b10010000110111 0
b100000 1
#170000
0#
#175000
1#
#177000
b1001 %
#180000
0#
#185000
1#
#187000
b110000001000010001000100011 !
b110000001000010001000100011 (
b110000001000010001000100011 ,
b100100 "
b100100 '
b1010 &
b110000001000010001000100011 0
b100100 1
#190000
0#
#195000
1#
#197000
b1010 %
#200000
0#
#205000
1#
#207000
b110010001000010010010000011 !
b110010001000010010010000011 (
b110010001000010010010000011 ,
b101000 "
b101000 '
b1011 &
b110010001000010010010000011 0
b101000 1
#210000
0#
#215000
1#
#217000
b1011 %
#220000
0#
#225000
1#
#227000
b100011001010010010011 !
b100011001010010010011 (
b100011001010010010011 ,
b101100 "
b101100 '
b1100 &
b100011001010010010011 0
b101100 1
#230000
0#
#235000
1#
#237000
b1100 %
#240000
0#
#245000
1#
#247000
b100010101010100010011 !
b100010101010100010011 (
b100010101010100010011 ,
b110000 "
b110000 '
b1101 &
b100010101010100010011 0
b110000 1
#250000
0#
#255000
1#
#257000
b1101 %
#260000
0#
#265000
1#
#267000
b1000000000100010101010110010011 !
b1000000000100010101010110010011 (
b1000000000100010101010110010011 ,
b110100 "
b110100 '
b1110 &
b1000000000100010101010110010011 0
b110100 1
#270000
0#
#275000
1#
#277000
b1110 %
#280000
0#
#285000
1#
#287000
b1000001000011001100011 !
b1000001000011001100011 (
b1000001000011001100011 ,
b111000 "
b111000 '
b1111 &
b1000001000011001100011 0
b111000 1
#290000
0#
#295000
1#
#297000
b1111 %
