register_file.v
module register_file (
    input wire clk,
    input wire reset,
    input wire [4:0] read_reg1,
    input wire [4:0] read_reg2,
    input wire [4:0] write_reg,
    input wire [63:0] write_data,
    input wire reg_write_en,
    output wire [63:0] read_data1,
    output wire [63:0] read_data2
);

    // 31 registers, each 64 bits
    reg [63:0] registers [31:0];

    integer i;
    initial begin
        for (i = 0; i < 32; i = i + 1) begin
            registers[i] = 64'b0;
        end
    end

    // Read data from registers
    assign read_data1 = registers[read_reg1];
    assign read_data2 = registers[read_reg2];

    // Write data to registers or reset all registers
    always @(posedge clk or posedge reset) begin
        if (reset) begin
            // Reset all registers to 0
            for (i = 0; i < 32; i = i + 1) begin
                registers[i] <= 64'b0;
            end
        end else if (reg_write_en && write_reg != 5'b0) begin
            // Normal write operation (register x0 is hardwired to 0)
            registers[write_reg] <= write_data;
        end
    end

endmodule

register_file_tb.v
`timescale 1ns/1ps
`include "register_file.v"
module register_file_tb;
    // Signals declaration
    reg clk;
    reg [4:0] read_reg1;
    reg [4:0] read_reg2;
    reg [4:0] write_reg;
    reg [63:0] write_data;
    reg reg_write_en;
    wire [63:0] read_data1;
    wire [63:0] read_data2;
    
    // Test counters
    integer test_count = 0;
    integer pass_count = 0;

    // Instantiate register file
    register_file dut (
        .clk(clk),
        .read_reg1(read_reg1),
        .read_reg2(read_reg2),
        .write_reg(write_reg),
        .write_data(write_data),
        .reg_write_en(reg_write_en),
        .read_data1(read_data1),
        .read_data2(read_data2)
    );

    // Clock generation
    always #5 clk = ~clk;

    // Test task
    task run_test;
        input [4:0] test_read_reg1;
        input [4:0] test_read_reg2;
        input [4:0] test_write_reg;
        input [63:0] test_write_data;
        input test_reg_write_en;
        input [63:0] expected_data1;
        input [63:0] expected_data2;
        input [127:0] test_name;  // Fixed: Using a reg array for the string
        begin
            test_count = test_count + 1;
            
            // Apply test inputs
            @(negedge clk);
            read_reg1 = test_read_reg1;
            read_reg2 = test_read_reg2;
            write_reg = test_write_reg;
            write_data = test_write_data;
            reg_write_en = test_reg_write_en;
            
            @(posedge clk);
            @(negedge clk);  // Wait for write to complete
            
            // Display test information
            $display("\nTest Case %0d: %s", test_count, test_name);
            $display("Inputs:");
            $display("  read_reg1 = %d", read_reg1);
            $display("  read_reg2 = %d", read_reg2);
            $display("  write_reg = %d", write_reg);
            $display("  write_data = %h", write_data);
            $display("  reg_write_en = %b", reg_write_en);
            
            // Compare results
            if (read_data1 === expected_data1 && read_data2 === expected_data2) begin
                $display("Status: PASS");
                $display("  read_data1 = %h (Expected: %h)", read_data1, expected_data1);
                $display("  read_data2 = %h (Expected: %h)", read_data2, expected_data2);
                pass_count = pass_count + 1;
            end else begin
                $display("Status: FAIL");
                $display("  read_data1 = %h (Expected: %h)", read_data1, expected_data1);
                $display("  read_data2 = %h (Expected: %h)", read_data2, expected_data2);
            end
        end
    endtask

    // Main test sequence
    initial begin
        // Initialize signals
        clk = 0;
        read_reg1 = 0;
        read_reg2 = 0;
        write_reg = 0;
        write_data = 0;
        reg_write_en = 0;

        #10;

        // Test 1: Verify x0 is hardwired to 0
        run_test(5'd0, 5'd0, 5'd0, 64'hFFFFFFFFFFFFFFFF, 1'b1, 
                64'h0, 64'h0, 
                "x0 hardwired to 0");

        #10;

        // Test 2: Write to reg1 and verify
        run_test(5'd1, 5'd0, 5'd1, 64'hDEADBEEFDEADBEEF, 1'b1, 
                64'hDEADBEEFDEADBEEF, 64'h0, 
                "Write to reg1");
        
        #10;

        // Test 3: Write to reg2 while reading reg1
        run_test(5'd1, 5'd2, 5'd2, 64'hCAFEBABECAFEBABE, 1'b1, 
                64'hDEADBEEFDEADBEEF, 64'hCAFEBABECAFEBABE, 
                "Write to reg2, read reg1");

        #10;

        // Test 4: Attempt write with reg_write_en=0
        run_test(5'd1, 5'd2, 5'd1, 64'h1111111111111111, 1'b0,
                64'hDEADBEEFDEADBEEF, 64'hCAFEBABECAFEBABE, 
                "Write disabled");

        #10;

        // Test 5: Write to x0 (should remain 0)
        run_test(5'd0, 5'd1, 5'd0, 64'hFFFFFFFFFFFFFFFF, 1'b1,
                64'h0, 64'hDEADBEEFDEADBEEF, 
                "Write to x0 (should be ignored)");

        #10;

        // Test 6: Write to last register (x31)
        run_test(5'd31, 5'd1, 5'd31, 64'h1234567890ABCDEF, 1'b1,
                64'h1234567890ABCDEF, 64'hDEADBEEFDEADBEEF, 
                "Write to x31");

        #10;

        // Test 7: Multiple reads of same register
        run_test(5'd2, 5'd2, 5'd3, 64'hAAAAAAAAAAAAAAAA, 1'b1,
                64'hCAFEBABECAFEBABE, 64'hCAFEBABECAFEBABE, 
                "Multiple reads of same register");

        #10;

        // Print test summary
        $display("\n=== Test Summary ===");
        $display("Total Tests: %0d", test_count);
        $display("Passed: %0d", pass_count);
        $display("Failed: %0d", test_count - pass_count);
        $display("==================\n");

        $finish;
    end

    // Generate VCD file
    initial begin
        $dumpfile("register_file_tb.vcd");
        $dumpvars(0, register_file_tb);
    end

endmodule

SEQ/register_file_tb.vcd
$date
	Fri Mar  7 06:17:55 2025
$end
$version
	Icarus Verilog
$end
$timescale
	1ps
$end
$scope module register_file_tb $end
$var wire 64 ! read_data2 [63:0] $end
$var wire 64 " read_data1 [63:0] $end
$var reg 1 # clk $end
$var reg 5 $ read_reg1 [4:0] $end
$var reg 5 % read_reg2 [4:0] $end
$var reg 1 & reg_write_en $end
$var reg 64 ' write_data [63:0] $end
$var reg 5 ( write_reg [4:0] $end
$var integer 32 ) pass_count [31:0] $end
$var integer 32 * test_count [31:0] $end
$scope module dut $end
$var wire 1 # clk $end
$var wire 64 + read_data1 [63:0] $end
$var wire 64 , read_data2 [63:0] $end
$var wire 5 - read_reg1 [4:0] $end
$var wire 5 . read_reg2 [4:0] $end
$var wire 1 & reg_write_en $end
$var wire 1 / reset $end
$var wire 64 0 write_data [63:0] $end
$var wire 5 1 write_reg [4:0] $end
$var integer 32 2 i [31:0] $end
$upscope $end
$scope task run_test $end
$var reg 64 3 expected_data1 [63:0] $end
$var reg 64 4 expected_data2 [63:0] $end
$var reg 128 5 test_name [127:0] $end
$var reg 5 6 test_read_reg1 [4:0] $end
$var reg 5 7 test_read_reg2 [4:0] $end
$var reg 1 8 test_reg_write_en $end
$var reg 64 9 test_write_data [63:0] $end
$var reg 5 : test_write_reg [4:0] $end
$upscope $end
$upscope $end
$enddefinitions $end
$comment Show the parameter values. $end
$dumpall
$end
#0
$dumpvars
bx :
bx 9
x8
bx 7
bx 6
bx 5
bx 4
bx 3
b100000 2
b0 1
b0 0
z/
b0 .
b0 -
b0 ,
b0 +
b0 *
b0 )
b0 (
b0 '
0&
b0 %
b0 $
0#
b0 "
b0 !
$end
#5000
1#
#10000
1&
b1111111111111111111111111111111111111111111111111111111111111111 '
b1111111111111111111111111111111111111111111111111111111111111111 0
0#
b1 *
b110000001000000110100001100001011100100110010001110111011010010111001001100101011001000010000001110100011011110010000000110000 5
b0 4
b0 3
18
b1111111111111111111111111111111111111111111111111111111111111111 9
b0 :
b0 7
b0 6
#15000
1#
#20000
b1 )
0#
#25000
1#
#30000
b1101111010101101101111101110111111011110101011011011111011101111 '
b1101111010101101101111101110111111011110101011011011111011101111 0
b1 (
b1 1
b1 $
b1 -
0#
b10 *
b1010111011100100110100101110100011001010010000001110100011011110010000001110010011001010110011100110001 5
b1101111010101101101111101110111111011110101011011011111011101111 3
b1101111010101101101111101110111111011110101011011011111011101111 9
b1 :
b1 6
#35000
b1101111010101101101111101110111111011110101011011011111011101111 "
b1101111010101101101111101110111111011110101011011011111011101111 +
1#
#40000
b10 )
0#
#45000
1#
#50000
b1100101011111110101110101011111011001010111111101011101010111110 '
b1100101011111110101110101011111011001010111111101011101010111110 0
b10 (
b10 1
b10 %
b10 .
0#
b11 *
b100000011100100110010101100111001100100010110000100000011100100110010101100001011001000010000001110010011001010110011100110001 5
b1100101011111110101110101011111011001010111111101011101010111110 4
b1100101011111110101110101011111011001010111111101011101010111110 9
b10 :
b10 7
#55000
b1100101011111110101110101011111011001010111111101011101010111110 !
b1100101011111110101110101011111011001010111111101011101010111110 ,
1#
#60000
b11 )
0#
#65000
1#
#70000
0&
b1000100010001000100010001000100010001000100010001000100010001 '
b1000100010001000100010001000100010001000100010001000100010001 0
b1 (
b1 1
0#
b100 *
b101011101110010011010010111010001100101001000000110010001101001011100110110000101100010011011000110010101100100 5
08
b1000100010001000100010001000100010001000100010001000100010001 9
b1 :
#75000
1#
#80000
b100 )
0#
#85000
1#
#90000
1&
b1111111111111111111111111111111111111111111111111111111111111111 '
b1111111111111111111111111111111111111111111111111111111111111111 0
b0 (
b0 1
b1101111010101101101111101110111111011110101011011011111011101111 !
b1101111010101101101111101110111111011110101011011011111011101111 ,
b1 %
b1 .
b0 "
b0 +
b0 $
b0 -
0#
b101 *
b1101111011101010110110001100100001000000110001001100101001000000110100101100111011011100110111101110010011001010110010000101001 5
b1101111010101101101111101110111111011110101011011011111011101111 4
b0 3
18
b1111111111111111111111111111111111111111111111111111111111111111 9
b0 :
b1 7
b0 6
#95000
1#
#100000
b101 )
0#
#105000
1#
#110000
b1001000110100010101100111100010010000101010111100110111101111 '
b1001000110100010101100111100010010000101010111100110111101111 0
b11111 (
b11111 1
b11111 $
b11111 -
0#
b110 *
b10101110111001001101001011101000110010100100000011101000110111100100000011110000011001100110001 5
b1001000110100010101100111100010010000101010111100110111101111 3
b1001000110100010101100111100010010000101010111100110111101111 9
b11111 :
b11111 6
#115000
b1001000110100010101100111100010010000101010111100110111101111 "
b1001000110100010101100111100010010000101010111100110111101111 +
1#
#120000
b110 )
0#
#125000
1#
#130000
b1010101010101010101010101010101010101010101010101010101010101010 '
b1010101010101010101010101010101010101010101010101010101010101010 0
b11 (
b11 1
b1100101011111110101110101011111011001010111111101011101010111110 !
b1100101011111110101110101011111011001010111111101011101010111110 ,
b10 %
b10 .
b1100101011111110101110101011111011001010111111101011101010111110 "
b1100101011111110101110101011111011001010111111101011101010111110 +
b10 $
b10 -
0#
b111 *
b1101111011001100010000001110011011000010110110101100101001000000111001001100101011001110110100101110011011101000110010101110010 5
b1100101011111110101110101011111011001010111111101011101010111110 4
b1100101011111110101110101011111011001010111111101011101010111110 3
b1010101010101010101010101010101010101010101010101010101010101010 9
b11 :
b10 7
b10 6
#135000
1#
#140000
b111 )
0#
